DGGSForPoly/__init__.py
DGGSForPoly/cell_area.py
DGGSForPoly/cell_helpers.py
DGGSForPoly/cell_plot.py
DGGSForPoly/poly_fill.py
DGGSForPoly-0.2.20.dist-info/LICENSE.md
DGGSForPoly-0.2.20.dist-info/METADATA
DGGSForPoly-0.2.20.dist-info/WHEEL
DGGSForPoly-0.2.20.dist-info/top_level.txt
DGGSForPoly-0.2.20.dist-info/RECORD
