Metadata-Version: 2.1
Name: DGGSForPoly
Version: 0.2.20
Summary: This package finds the rHEALPIX dggs cells for Polygons using the rhgealpix dggs engine.
Home-page: https://github.com/CSIRO-enviro-informatics/DGGSForPoly
Author: Ross Petridis
Author-email: ross.petridis@csiro.au
License: UNKNOWN
Project-URL: Bug Tracker, https://github.com/CSIRO-enviro-informatics/DGGSForPoly/issues
Platform: UNKNOWN
License-File: LICENSE.md
Requires-Dist: Shapely
Requires-Dist: rhealpixdggs
